{
  "Name": "ROM",
  "Colour": "#82A60F",
  "InputPins": [
    {
      "Name": "CE",
      "ID": 895670238,
      "PositionY": -2.395833,
      "ColourThemeName": "Red"
    },
    {
      "Name": "D0",
      "ID": 1029887736,
      "PositionY": 3.90625,
      "ColourThemeName": "Red"
    },
    {
      "Name": "D1",
      "ID": 1728542386,
      "PositionY": 3.359375,
      "ColourThemeName": "Red"
    },
    {
      "Name": "D2",
      "ID": 260001113,
      "PositionY": 2.916667,
      "ColourThemeName": "Red"
    },
    {
      "Name": "D3",
      "ID": 314984729,
      "PositionY": 2.36979175,
      "ColourThemeName": "Red"
    },
    {
      "Name": "D4",
      "ID": 543432340,
      "PositionY": 1.86197937,
      "ColourThemeName": "Red"
    },
    {
      "Name": "D5",
      "ID": 1019580186,
      "PositionY": 1.315104,
      "ColourThemeName": "Red"
    },
    {
      "Name": "D6",
      "ID": 125537461,
      "PositionY": 0.8203134,
      "ColourThemeName": "Red"
    },
    {
      "Name": "D7",
      "ID": 918834159,
      "PositionY": 0.33854115,
      "ColourThemeName": "Red"
    },
    {
      "Name": "nPRESET",
      "ID": 208090654,
      "PositionY": 4.49218845,
      "ColourThemeName": "Red"
    },
    {
      "Name": "nCLEAR",
      "ID": 849723161,
      "PositionY": -4.075521,
      "ColourThemeName": "Red"
    },
    {
      "Name": "nCLK",
      "ID": 601063150,
      "PositionY": -3.489584,
      "ColourThemeName": "Red"
    },
    {
      "Name": "A0",
      "ID": 1358673712,
      "PositionY": -0.325520635,
      "ColourThemeName": "Red"
    },
    {
      "Name": "A1",
      "ID": 363156619,
      "PositionY": -1.002604,
      "ColourThemeName": "Red"
    },
    {
      "Name": "A2",
      "ID": 1491206072,
      "PositionY": -1.497396,
      "ColourThemeName": "Red"
    },
    {
      "Name": "A3",
      "ID": 237519186,
      "PositionY": -1.940104,
      "ColourThemeName": "Red"
    },
    {
      "Name": "OE",
      "ID": 1860275856,
      "PositionY": -2.734376,
      "ColourThemeName": "Red"
    },
    {
      "Name": "WE",
      "ID": 1116171393,
      "PositionY": -2.98177052,
      "ColourThemeName": "Red"
    }
  ],
  "OutputPins": [
    {
      "Name": "Pin",
      "ID": 1065016072,
      "PositionY": 2.552083,
      "ColourThemeName": "Red"
    },
    {
      "Name": "Pin",
      "ID": 1237120903,
      "PositionY": 1.57552063,
      "ColourThemeName": "Red"
    },
    {
      "Name": "Pin",
      "ID": 791246091,
      "PositionY": 0.833333135,
      "ColourThemeName": "Red"
    },
    {
      "Name": "Pin",
      "ID": 57269111,
      "PositionY": 0.0651043653,
      "ColourThemeName": "Red"
    },
    {
      "Name": "Pin",
      "ID": 234621574,
      "PositionY": -0.559895933,
      "ColourThemeName": "Red"
    },
    {
      "Name": "Pin",
      "ID": 45168748,
      "PositionY": -1.263021,
      "ColourThemeName": "Red"
    },
    {
      "Name": "Pin",
      "ID": 1286999518,
      "PositionY": -1.861979,
      "ColourThemeName": "Red"
    },
    {
      "Name": "Pin",
      "ID": 1102346338,
      "PositionY": -2.682292,
      "ColourThemeName": "Red"
    }
  ],
  "SubChips": [
    {
      "Name": "Partial ROM",
      "ID": 37175291,
      "Points": [
        {
          "X": 0.858955264,
          "Y": 0.169271231
        }
      ],
      "Data": null
    },
    {
      "Name": "TRI-STATE BUFFER",
      "ID": 1197882810,
      "Points": [
        {
          "X": 5.15373325,
          "Y": 3.177083
        }
      ],
      "Data": null
    },
    {
      "Name": "TRI-STATE BUFFER",
      "ID": 690654449,
      "Points": [
        {
          "X": 5.15373325,
          "Y": 2.38729239
        }
      ],
      "Data": null
    },
    {
      "Name": "TRI-STATE BUFFER",
      "ID": 903535338,
      "Points": [
        {
          "X": 5.15373325,
          "Y": 1.65229237
        }
      ],
      "Data": null
    },
    {
      "Name": "TRI-STATE BUFFER",
      "ID": 528532735,
      "Points": [
        {
          "X": 5.15373325,
          "Y": 0.9172921
        }
      ],
      "Data": null
    },
    {
      "Name": "TRI-STATE BUFFER",
      "ID": 1272674264,
      "Points": [
        {
          "X": 5.15373325,
          "Y": 0.182291865
        }
      ],
      "Data": null
    },
    {
      "Name": "TRI-STATE BUFFER",
      "ID": 1296671691,
      "Points": [
        {
          "X": 5.15373325,
          "Y": -0.5527084
        }
      ],
      "Data": null
    },
    {
      "Name": "TRI-STATE BUFFER",
      "ID": 592810159,
      "Points": [
        {
          "X": 5.15373325,
          "Y": -1.28770864
        }
      ],
      "Data": null
    },
    {
      "Name": "TRI-STATE BUFFER",
      "ID": 1675136219,
      "Points": [
        {
          "X": 5.15373325,
          "Y": -2.022709
        }
      ],
      "Data": null
    },
    {
      "Name": "BUS",
      "ID": 76247055,
      "Points": [
        {
          "X": 2.49878049,
          "Y": -2.916667
        },
        {
          "X": 2.47275162,
          "Y": 4.2578125
        }
      ],
      "Data": null
    },
    {
      "Name": "BUS",
      "ID": 546716766,
      "Points": [
        {
          "X": -6.689442,
          "Y": -4.0625
        },
        {
          "X": -6.676428,
          "Y": 4.6875
        }
      ],
      "Data": null
    },
    {
      "Name": "TRI-STATE BUFFER",
      "ID": 332182145,
      "Points": [
        {
          "X": -3.72214127,
          "Y": 3.73135471
        }
      ],
      "Data": null
    },
    {
      "Name": "TRI-STATE BUFFER",
      "ID": 386915431,
      "Points": [
        {
          "X": -3.73515534,
          "Y": 2.931251
        }
      ],
      "Data": null
    },
    {
      "Name": "TRI-STATE BUFFER",
      "ID": 254918795,
      "Points": [
        {
          "X": -3.81324267,
          "Y": 1.519167
        }
      ],
      "Data": null
    },
    {
      "Name": "TRI-STATE BUFFER",
      "ID": 1306827798,
      "Points": [
        {
          "X": -3.82625723,
          "Y": 0.7841667
        }
      ],
      "Data": null
    },
    {
      "Name": "TRI-STATE BUFFER",
      "ID": 1318024676,
      "Points": [
        {
          "X": -3.81324267,
          "Y": 0.04916644
        }
      ],
      "Data": null
    },
    {
      "Name": "TRI-STATE BUFFER",
      "ID": 242017698,
      "Points": [
        {
          "X": -3.81324267,
          "Y": -0.685833752
        }
      ],
      "Data": null
    },
    {
      "Name": "TRI-STATE BUFFER",
      "ID": 1219858055,
      "Points": [
        {
          "X": -3.81324267,
          "Y": -1.42083406
        }
      ],
      "Data": null
    },
    {
      "Name": "TRI-STATE BUFFER",
      "ID": 791435634,
      "Points": [
        {
          "X": -3.73515582,
          "Y": 2.2265625
        }
      ],
      "Data": null
    }
  ],
  "Connections": [
    {
      "Source": {
        "PinType": 4,
        "SubChipID": 76247055,
        "PinID": 1
      },
      "Target": {
        "PinType": 3,
        "SubChipID": 1197882810,
        "PinID": 0
      },
      "WirePoints": [
        {
          "X": 2.47596431,
          "Y": 3.37231255
        },
        {
          "X": 4.233733,
          "Y": 3.352083
        }
      ],
      "ColourThemeName": "Blue"
    },
    {
      "Source": {
        "PinType": 4,
        "SubChipID": 76247055,
        "PinID": 1
      },
      "Target": {
        "PinType": 3,
        "SubChipID": 690654449,
        "PinID": 0
      },
      "WirePoints": [
        {
          "X": 2.47893977,
          "Y": 2.55215216
        },
        {
          "X": 4.233733,
          "Y": 2.56229234
        }
      ],
      "ColourThemeName": "Blue"
    },
    {
      "Source": {
        "PinType": 4,
        "SubChipID": 76247055,
        "PinID": 1
      },
      "Target": {
        "PinType": 3,
        "SubChipID": 903535338,
        "PinID": 0
      },
      "WirePoints": [
        {
          "X": 2.48158479,
          "Y": 1.82309055
        },
        {
          "X": 4.233733,
          "Y": 1.82729244
        }
      ],
      "ColourThemeName": "Blue"
    },
    {
      "Source": {
        "PinType": 4,
        "SubChipID": 76247055,
        "PinID": 1
      },
      "Target": {
        "PinType": 3,
        "SubChipID": 528532735,
        "PinID": 0
      },
      "WirePoints": [
        {
          "X": 2.48437238,
          "Y": 1.05472946
        },
        {
          "X": 4.233733,
          "Y": 1.09229207
        }
      ],
      "ColourThemeName": "Blue"
    },
    {
      "Source": {
        "PinType": 4,
        "SubChipID": 76247055,
        "PinID": 1
      },
      "Target": {
        "PinType": 3,
        "SubChipID": 1272674264,
        "PinID": 0
      },
      "WirePoints": [
        {
          "X": 2.48711276,
          "Y": 0.299342632
        },
        {
          "X": 4.233733,
          "Y": 0.357291877
        }
      ],
      "ColourThemeName": "Blue"
    },
    {
      "Source": {
        "PinType": 4,
        "SubChipID": 76247055,
        "PinID": 1
      },
      "Target": {
        "PinType": 3,
        "SubChipID": 1296671691,
        "PinID": 0
      },
      "WirePoints": [
        {
          "X": 2.48947453,
          "Y": -0.351596355
        },
        {
          "X": 4.233733,
          "Y": -0.377708375
        }
      ],
      "ColourThemeName": "Blue"
    },
    {
      "Source": {
        "PinType": 4,
        "SubChipID": 76247055,
        "PinID": 1
      },
      "Target": {
        "PinType": 3,
        "SubChipID": 592810159,
        "PinID": 0
      },
      "WirePoints": [
        {
          "X": 2.49226117,
          "Y": -1.11972082
        },
        {
          "X": 4.233733,
          "Y": -1.11270857
        }
      ],
      "ColourThemeName": "Blue"
    },
    {
      "Source": {
        "PinType": 4,
        "SubChipID": 76247055,
        "PinID": 1
      },
      "Target": {
        "PinType": 3,
        "SubChipID": 1675136219,
        "PinID": 0
      },
      "WirePoints": [
        {
          "X": 2.49467087,
          "Y": -1.78391612
        },
        {
          "X": 4.233733,
          "Y": -1.847709
        }
      ],
      "ColourThemeName": "Blue"
    },
    {
      "Source": {
        "PinType": 4,
        "SubChipID": 37175291,
        "PinID": 1594307951
      },
      "Target": {
        "PinType": 3,
        "SubChipID": 1197882810,
        "PinID": 1
      },
      "WirePoints": [
        {
          "X": 1.63395524,
          "Y": 1.9692713
        },
        {
          "X": 4.233733,
          "Y": 3.002083
        }
      ],
      "ColourThemeName": "Red"
    },
    {
      "Source": {
        "PinType": 4,
        "SubChipID": 37175291,
        "PinID": 1656966135
      },
      "Target": {
        "PinType": 3,
        "SubChipID": 690654449,
        "PinID": 1
      },
      "WirePoints": [
        {
          "X": 1.63395524,
          "Y": 1.4549855
        },
        {
          "X": 4.233733,
          "Y": 2.21229243
        }
      ],
      "ColourThemeName": "Red"
    },
    {
      "Source": {
        "PinType": 4,
        "SubChipID": 37175291,
        "PinID": 1418673854
      },
      "Target": {
        "PinType": 3,
        "SubChipID": 903535338,
        "PinID": 1
      },
      "WirePoints": [
        {
          "X": 1.63395524,
          "Y": 0.9406998
        },
        {
          "X": 4.233733,
          "Y": 1.4772923
        }
      ],
      "ColourThemeName": "Red"
    },
    {
      "Source": {
        "PinType": 4,
        "SubChipID": 37175291,
        "PinID": 1602149888
      },
      "Target": {
        "PinType": 3,
        "SubChipID": 528532735,
        "PinID": 1
      },
      "WirePoints": [
        {
          "X": 1.63395524,
          "Y": 0.426414073
        },
        {
          "X": 4.233733,
          "Y": 0.7422921
        }
      ],
      "ColourThemeName": "Red"
    },
    {
      "Source": {
        "PinType": 4,
        "SubChipID": 37175291,
        "PinID": 499424700
      },
      "Target": {
        "PinType": 3,
        "SubChipID": 1272674264,
        "PinID": 1
      },
      "WirePoints": [
        {
          "X": 1.63395524,
          "Y": -0.08787173
        },
        {
          "X": 4.233733,
          "Y": 0.00729185343
        }
      ],
      "ColourThemeName": "Red"
    },
    {
      "Source": {
        "PinType": 4,
        "SubChipID": 37175291,
        "PinID": 1400405084
      },
      "Target": {
        "PinType": 3,
        "SubChipID": 1296671691,
        "PinID": 1
      },
      "WirePoints": [
        {
          "X": 1.63395524,
          "Y": -0.6021574
        },
        {
          "X": 4.233733,
          "Y": -0.7277084
        }
      ],
      "ColourThemeName": "Red"
    },
    {
      "Source": {
        "PinType": 4,
        "SubChipID": 37175291,
        "PinID": 899580047
      },
      "Target": {
        "PinType": 3,
        "SubChipID": 592810159,
        "PinID": 1
      },
      "WirePoints": [
        {
          "X": 1.63395524,
          "Y": -1.11644316
        },
        {
          "X": 4.233733,
          "Y": -1.46270871
        }
      ],
      "ColourThemeName": "Red"
    },
    {
      "Source": {
        "PinType": 4,
        "SubChipID": 37175291,
        "PinID": 989150082
      },
      "Target": {
        "PinType": 3,
        "SubChipID": 1675136219,
        "PinID": 1
      },
      "WirePoints": [
        {
          "X": 1.63395524,
          "Y": -1.63072884
        },
        {
          "X": 4.233733,
          "Y": -2.19770885
        }
      ],
      "ColourThemeName": "Red"
    },
    {
      "Source": {
        "PinType": 4,
        "SubChipID": 1197882810,
        "PinID": 2
      },
      "Target": {
        "PinType": 2,
        "SubChipID": 0,
        "PinID": 1065016072
      },
      "WirePoints": [
        {
          "X": 6.07373333,
          "Y": 3.177083
        },
        {
          "X": 7.837778,
          "Y": 2.552083
        }
      ],
      "ColourThemeName": "Red"
    },
    {
      "Source": {
        "PinType": 4,
        "SubChipID": 690654449,
        "PinID": 2
      },
      "Target": {
        "PinType": 2,
        "SubChipID": 0,
        "PinID": 1237120903
      },
      "WirePoints": [
        {
          "X": 6.07373333,
          "Y": 2.38729239
        },
        {
          "X": 7.837778,
          "Y": 1.57552063
        }
      ],
      "ColourThemeName": "Red"
    },
    {
      "Source": {
        "PinType": 4,
        "SubChipID": 903535338,
        "PinID": 2
      },
      "Target": {
        "PinType": 2,
        "SubChipID": 0,
        "PinID": 791246091
      },
      "WirePoints": [
        {
          "X": 6.07373333,
          "Y": 1.65229237
        },
        {
          "X": 7.837778,
          "Y": 0.833333135
        }
      ],
      "ColourThemeName": "Red"
    },
    {
      "Source": {
        "PinType": 4,
        "SubChipID": 528532735,
        "PinID": 2
      },
      "Target": {
        "PinType": 2,
        "SubChipID": 0,
        "PinID": 57269111
      },
      "WirePoints": [
        {
          "X": 6.07373333,
          "Y": 0.9172921
        },
        {
          "X": 7.837778,
          "Y": 0.0651043653
        }
      ],
      "ColourThemeName": "Red"
    },
    {
      "Source": {
        "PinType": 4,
        "SubChipID": 1272674264,
        "PinID": 2
      },
      "Target": {
        "PinType": 2,
        "SubChipID": 0,
        "PinID": 234621574
      },
      "WirePoints": [
        {
          "X": 6.07373333,
          "Y": 0.182291865
        },
        {
          "X": 7.837778,
          "Y": -0.559895933
        }
      ],
      "ColourThemeName": "Red"
    },
    {
      "Source": {
        "PinType": 4,
        "SubChipID": 1296671691,
        "PinID": 2
      },
      "Target": {
        "PinType": 2,
        "SubChipID": 0,
        "PinID": 45168748
      },
      "WirePoints": [
        {
          "X": 6.07373333,
          "Y": -0.5527084
        },
        {
          "X": 7.837778,
          "Y": -1.263021
        }
      ],
      "ColourThemeName": "Red"
    },
    {
      "Source": {
        "PinType": 4,
        "SubChipID": 592810159,
        "PinID": 2
      },
      "Target": {
        "PinType": 2,
        "SubChipID": 0,
        "PinID": 1286999518
      },
      "WirePoints": [
        {
          "X": 6.07373333,
          "Y": -1.28770864
        },
        {
          "X": 7.837778,
          "Y": -1.861979
        }
      ],
      "ColourThemeName": "Red"
    },
    {
      "Source": {
        "PinType": 4,
        "SubChipID": 1675136219,
        "PinID": 2
      },
      "Target": {
        "PinType": 2,
        "SubChipID": 0,
        "PinID": 1102346338
      },
      "WirePoints": [
        {
          "X": 6.07373333,
          "Y": -2.022709
        },
        {
          "X": 7.837778,
          "Y": -2.682292
        }
      ],
      "ColourThemeName": "Red"
    },
    {
      "Source": {
        "PinType": 1,
        "SubChipID": 0,
        "PinID": 208090654
      },
      "Target": {
        "PinType": 3,
        "SubChipID": 37175291,
        "PinID": 305268403
      },
      "WirePoints": [
        {
          "X": -7.837778,
          "Y": 4.49218845
        },
        {
          "X": -1.02814364,
          "Y": 3.8671875
        },
        {
          "X": -1.093216,
          "Y": 2.291667
        },
        {
          "X": 0.08395529,
          "Y": 1.9692713
        }
      ],
      "ColourThemeName": "Red"
    },
    {
      "Source": {
        "PinType": 1,
        "SubChipID": 0,
        "PinID": 601063150
      },
      "Target": {
        "PinType": 3,
        "SubChipID": 37175291,
        "PinID": 619427673
      },
      "WirePoints": [
        {
          "X": -7.837778,
          "Y": -3.489584
        },
        {
          "X": 0.08395529,
          "Y": -1.39072883
        }
      ],
      "ColourThemeName": "Red"
    },
    {
      "Source": {
        "PinType": 1,
        "SubChipID": 0,
        "PinID": 895670238
      },
      "Target": {
        "PinType": 3,
        "SubChipID": 37175291,
        "PinID": 2088299077
      },
      "WirePoints": [
        {
          "X": -7.837778,
          "Y": -2.395833
        },
        {
          "X": 0.08395529,
          "Y": -1.15072882
        }
      ],
      "ColourThemeName": "Red"
    },
    {
      "Source": {
        "PinType": 1,
        "SubChipID": 0,
        "PinID": 1358673712
      },
      "Target": {
        "PinType": 3,
        "SubChipID": 37175291,
        "PinID": 149091278
      },
      "WirePoints": [
        {
          "X": -7.837778,
          "Y": -0.325520635
        },
        {
          "X": 0.08395529,
          "Y": -0.190728873
        }
      ],
      "ColourThemeName": "Green"
    },
    {
      "Source": {
        "PinType": 1,
        "SubChipID": 0,
        "PinID": 363156619
      },
      "Target": {
        "PinType": 3,
        "SubChipID": 37175291,
        "PinID": 1927298473
      },
      "WirePoints": [
        {
          "X": -7.837778,
          "Y": -1.002604
        },
        {
          "X": 0.08395529,
          "Y": -0.430728853
        }
      ],
      "ColourThemeName": "Green"
    },
    {
      "Source": {
        "PinType": 1,
        "SubChipID": 0,
        "PinID": 1491206072
      },
      "Target": {
        "PinType": 3,
        "SubChipID": 37175291,
        "PinID": 558737770
      },
      "WirePoints": [
        {
          "X": -7.837778,
          "Y": -1.497396
        },
        {
          "X": 0.08395529,
          "Y": -0.670728862
        }
      ],
      "ColourThemeName": "Green"
    },
    {
      "Source": {
        "PinType": 1,
        "SubChipID": 0,
        "PinID": 237519186
      },
      "Target": {
        "PinType": 3,
        "SubChipID": 37175291,
        "PinID": 856817436
      },
      "WirePoints": [
        {
          "X": -7.837778,
          "Y": -1.940104
        },
        {
          "X": 0.08395529,
          "Y": -0.9107288
        }
      ],
      "ColourThemeName": "Green"
    },
    {
      "Source": {
        "PinType": 1,
        "SubChipID": 0,
        "PinID": 1860275856
      },
      "Target": {
        "PinType": 3,
        "SubChipID": 76247055,
        "PinID": 0
      },
      "WirePoints": [
        {
          "X": -7.837778,
          "Y": -2.734376
        },
        {
          "X": 2.496985,
          "Y": -2.421787
        }
      ],
      "ColourThemeName": "Blue"
    },
    {
      "Source": {
        "PinType": 4,
        "SubChipID": 546716766,
        "PinID": 1
      },
      "Target": {
        "PinType": 3,
        "SubChipID": 332182145,
        "PinID": 0
      },
      "WirePoints": [
        {
          "X": -6.678655,
          "Y": 3.19010782
        },
        {
          "X": -4.64214134,
          "Y": 3.90635467
        }
      ],
      "ColourThemeName": "Blue"
    },
    {
      "Source": {
        "PinType": 4,
        "SubChipID": 546716766,
        "PinID": 1
      },
      "Target": {
        "PinType": 3,
        "SubChipID": 386915431,
        "PinID": 0
      },
      "WirePoints": [
        {
          "X": -6.679817,
          "Y": 2.40885925
        },
        {
          "X": -4.655155,
          "Y": 3.106251
        }
      ],
      "ColourThemeName": "Blue"
    },
    {
      "Source": {
        "PinType": 4,
        "SubChipID": 546716766,
        "PinID": 1
      },
      "Target": {
        "PinType": 3,
        "SubChipID": 254918795,
        "PinID": 0
      },
      "WirePoints": [
        {
          "X": -6.68082428,
          "Y": 1.73175764
        },
        {
          "X": -4.73324251,
          "Y": 1.6941669
        }
      ],
      "ColourThemeName": "Blue"
    },
    {
      "Source": {
        "PinType": 4,
        "SubChipID": 546716766,
        "PinID": 1
      },
      "Target": {
        "PinType": 3,
        "SubChipID": 1306827798,
        "PinID": 0
      },
      "WirePoints": [
        {
          "X": -6.682025,
          "Y": 0.9243717
        },
        {
          "X": -4.74625731,
          "Y": 0.9591667
        }
      ],
      "ColourThemeName": "Blue"
    },
    {
      "Source": {
        "PinType": 4,
        "SubChipID": 546716766,
        "PinID": 1
      },
      "Target": {
        "PinType": 3,
        "SubChipID": 1318024676,
        "PinID": 0
      },
      "WirePoints": [
        {
          "X": -6.68308973,
          "Y": 0.208362579
        },
        {
          "X": -4.73324251,
          "Y": 0.224166453
        }
      ],
      "ColourThemeName": "Blue"
    },
    {
      "Source": {
        "PinType": 4,
        "SubChipID": 546716766,
        "PinID": 1
      },
      "Target": {
        "PinType": 3,
        "SubChipID": 242017698,
        "PinID": 0
      },
      "WirePoints": [
        {
          "X": -6.68407774,
          "Y": -0.4557562
        },
        {
          "X": -4.73324251,
          "Y": -0.51083374
        }
      ],
      "ColourThemeName": "Blue"
    },
    {
      "Source": {
        "PinType": 4,
        "SubChipID": 546716766,
        "PinID": 1
      },
      "Target": {
        "PinType": 3,
        "SubChipID": 1219858055,
        "PinID": 0
      },
      "WirePoints": [
        {
          "X": -6.68512344,
          "Y": -1.15887976
        },
        {
          "X": -4.73324251,
          "Y": -1.24583411
        }
      ],
      "ColourThemeName": "Blue"
    },
    {
      "Source": {
        "PinType": 1,
        "SubChipID": 0,
        "PinID": 1116171393
      },
      "Target": {
        "PinType": 3,
        "SubChipID": 546716766,
        "PinID": 0
      },
      "WirePoints": [
        {
          "X": -7.837778,
          "Y": -2.98177052
        },
        {
          "X": -6.68787336,
          "Y": -3.007815
        }
      ],
      "ColourThemeName": "Blue"
    },
    {
      "Source": {
        "PinType": 1,
        "SubChipID": 0,
        "PinID": 1029887736
      },
      "Target": {
        "PinType": 3,
        "SubChipID": 332182145,
        "PinID": 1
      },
      "WirePoints": [
        {
          "X": -7.837778,
          "Y": 3.90625
        },
        {
          "X": -4.64214134,
          "Y": 3.55635476
        }
      ],
      "ColourThemeName": "Red"
    },
    {
      "Source": {
        "PinType": 1,
        "SubChipID": 0,
        "PinID": 1728542386
      },
      "Target": {
        "PinType": 3,
        "SubChipID": 386915431,
        "PinID": 1
      },
      "WirePoints": [
        {
          "X": -7.837778,
          "Y": 3.359375
        },
        {
          "X": -4.655155,
          "Y": 2.756251
        }
      ],
      "ColourThemeName": "Red"
    },
    {
      "Source": {
        "PinType": 1,
        "SubChipID": 0,
        "PinID": 314984729
      },
      "Target": {
        "PinType": 3,
        "SubChipID": 254918795,
        "PinID": 1
      },
      "WirePoints": [
        {
          "X": -7.837778,
          "Y": 2.36979175
        },
        {
          "X": -4.73324251,
          "Y": 1.344167
        }
      ],
      "ColourThemeName": "Red"
    },
    {
      "Source": {
        "PinType": 1,
        "SubChipID": 0,
        "PinID": 543432340
      },
      "Target": {
        "PinType": 3,
        "SubChipID": 1306827798,
        "PinID": 1
      },
      "WirePoints": [
        {
          "X": -7.837778,
          "Y": 1.86197937
        },
        {
          "X": -4.74625731,
          "Y": 0.6091667
        }
      ],
      "ColourThemeName": "Red"
    },
    {
      "Source": {
        "PinType": 1,
        "SubChipID": 0,
        "PinID": 1019580186
      },
      "Target": {
        "PinType": 3,
        "SubChipID": 1318024676,
        "PinID": 1
      },
      "WirePoints": [
        {
          "X": -7.837778,
          "Y": 1.315104
        },
        {
          "X": -4.73324251,
          "Y": -0.125833571
        }
      ],
      "ColourThemeName": "Red"
    },
    {
      "Source": {
        "PinType": 1,
        "SubChipID": 0,
        "PinID": 125537461
      },
      "Target": {
        "PinType": 3,
        "SubChipID": 242017698,
        "PinID": 1
      },
      "WirePoints": [
        {
          "X": -7.837778,
          "Y": 0.8203134
        },
        {
          "X": -4.73324251,
          "Y": -0.860833764
        }
      ],
      "ColourThemeName": "Red"
    },
    {
      "Source": {
        "PinType": 1,
        "SubChipID": 0,
        "PinID": 918834159
      },
      "Target": {
        "PinType": 3,
        "SubChipID": 1219858055,
        "PinID": 1
      },
      "WirePoints": [
        {
          "X": -7.837778,
          "Y": 0.33854115
        },
        {
          "X": -4.73324251,
          "Y": -1.595834
        }
      ],
      "ColourThemeName": "Red"
    },
    {
      "Source": {
        "PinType": 1,
        "SubChipID": 0,
        "PinID": 260001113
      },
      "Target": {
        "PinType": 3,
        "SubChipID": 791435634,
        "PinID": 1
      },
      "WirePoints": [
        {
          "X": -7.837778,
          "Y": 2.916667
        },
        {
          "X": -4.65515566,
          "Y": 2.05156255
        }
      ],
      "ColourThemeName": "Red"
    },
    {
      "Source": {
        "PinType": 4,
        "SubChipID": 546716766,
        "PinID": 1
      },
      "Target": {
        "PinType": 3,
        "SubChipID": 791435634,
        "PinID": 0
      },
      "WirePoints": [
        {
          "X": -6.68003,
          "Y": 2.265572
        },
        {
          "X": -4.65515566,
          "Y": 2.40156245
        }
      ],
      "ColourThemeName": "Blue"
    },
    {
      "Source": {
        "PinType": 4,
        "SubChipID": 332182145,
        "PinID": 2
      },
      "Target": {
        "PinType": 3,
        "SubChipID": 37175291,
        "PinID": 1622523213
      },
      "WirePoints": [
        {
          "X": -2.80214119,
          "Y": 3.73135471
        },
        {
          "X": 0.08395529,
          "Y": 1.72927129
        }
      ],
      "ColourThemeName": "Red"
    },
    {
      "Source": {
        "PinType": 4,
        "SubChipID": 386915431,
        "PinID": 2
      },
      "Target": {
        "PinType": 3,
        "SubChipID": 37175291,
        "PinID": 1092402226
      },
      "WirePoints": [
        {
          "X": -2.81515527,
          "Y": 2.931251
        },
        {
          "X": 0.08395529,
          "Y": 1.48927128
        }
      ],
      "ColourThemeName": "Red"
    },
    {
      "Source": {
        "PinType": 4,
        "SubChipID": 791435634,
        "PinID": 2
      },
      "Target": {
        "PinType": 3,
        "SubChipID": 37175291,
        "PinID": 1024454846
      },
      "WirePoints": [
        {
          "X": -2.81515574,
          "Y": 2.2265625
        },
        {
          "X": 0.08395529,
          "Y": 1.24927127
        }
      ],
      "ColourThemeName": "Red"
    },
    {
      "Source": {
        "PinType": 4,
        "SubChipID": 254918795,
        "PinID": 2
      },
      "Target": {
        "PinType": 3,
        "SubChipID": 37175291,
        "PinID": 286261674
      },
      "WirePoints": [
        {
          "X": -2.8932426,
          "Y": 1.519167
        },
        {
          "X": 0.08395529,
          "Y": 1.00927114
        }
      ],
      "ColourThemeName": "Red"
    },
    {
      "Source": {
        "PinType": 4,
        "SubChipID": 1306827798,
        "PinID": 2
      },
      "Target": {
        "PinType": 3,
        "SubChipID": 37175291,
        "PinID": 596006047
      },
      "WirePoints": [
        {
          "X": -2.90625715,
          "Y": 0.7841667
        },
        {
          "X": 0.08395529,
          "Y": 0.7692712
        }
      ],
      "ColourThemeName": "Red"
    },
    {
      "Source": {
        "PinType": 4,
        "SubChipID": 1318024676,
        "PinID": 2
      },
      "Target": {
        "PinType": 3,
        "SubChipID": 37175291,
        "PinID": 537700883
      },
      "WirePoints": [
        {
          "X": -2.8932426,
          "Y": 0.04916644
        },
        {
          "X": 0.08395529,
          "Y": 0.529271245
        }
      ],
      "ColourThemeName": "Red"
    },
    {
      "Source": {
        "PinType": 4,
        "SubChipID": 242017698,
        "PinID": 2
      },
      "Target": {
        "PinType": 3,
        "SubChipID": 37175291,
        "PinID": 83155279
      },
      "WirePoints": [
        {
          "X": -2.8932426,
          "Y": -0.685833752
        },
        {
          "X": 0.08395529,
          "Y": 0.289271235
        }
      ],
      "ColourThemeName": "Red"
    },
    {
      "Source": {
        "PinType": 4,
        "SubChipID": 1219858055,
        "PinID": 2
      },
      "Target": {
        "PinType": 3,
        "SubChipID": 37175291,
        "PinID": 104462183
      },
      "WirePoints": [
        {
          "X": -2.8932426,
          "Y": -1.42083406
        },
        {
          "X": 0.08395529,
          "Y": 0.04927113
        }
      ],
      "ColourThemeName": "Red"
    },
    {
      "Source": {
        "PinType": 1,
        "SubChipID": 0,
        "PinID": 849723161
      },
      "Target": {
        "PinType": 3,
        "SubChipID": 37175291,
        "PinID": 1200246824
      },
      "WirePoints": [
        {
          "X": -7.837778,
          "Y": -4.075521
        },
        {
          "X": 0.09110133,
          "Y": -3.7890625
        },
        {
          "X": 0.08395529,
          "Y": -1.63072884
        }
      ],
      "ColourThemeName": "Red"
    }
  ]
}